goose_talk_to_me/__init__.py
goose_talk_to_me/talk_to_me.py
goose_talk_to_me-0.3.2.dist-info/LICENSE
goose_talk_to_me-0.3.2.dist-info/METADATA
goose_talk_to_me-0.3.2.dist-info/WHEEL
goose_talk_to_me-0.3.2.dist-info/entry_points.txt
goose_talk_to_me-0.3.2.dist-info/top_level.txt
goose_talk_to_me-0.3.2.dist-info/RECORD
