Metadata-Version: 2.1
Name: goose-talk-to-me
Version: 0.3.2
Summary: A voice interaction plugin for your goose
Author-email: Max Novich <mnovich@squareup.com>
Requires-Python: >=3.10
License-File: LICENSE
Requires-Dist: goose-ai >=0.9.0
Requires-Dist: openai-whisper ==v20240930
Requires-Dist: sounddevice ==0.4.4
Requires-Dist: soundfile ==0.12.1
Requires-Dist: numpy ==2.0.1
Requires-Dist: scipy ==1.14.1
Requires-Dist: torch ==2.4.0
Requires-Dist: numba ==0.60.0
Requires-Dist: more-itertools ==10.4.0
Requires-Dist: ffmpeg ==1.4
Requires-Dist: pyobjc >=10.3.1
Requires-Dist: pyttsx3 ==2.98
